odoo/addons/sale_validity_auto_cancel/README.rst
odoo/addons/sale_validity_auto_cancel/__init__.py
odoo/addons/sale_validity_auto_cancel/__manifest__.py
odoo/addons/sale_validity_auto_cancel/data/ir_cron.xml
odoo/addons/sale_validity_auto_cancel/i18n/it.po
odoo/addons/sale_validity_auto_cancel/i18n/sale_validity_auto_cancel.pot
odoo/addons/sale_validity_auto_cancel/models/__init__.py
odoo/addons/sale_validity_auto_cancel/models/res_company.py
odoo/addons/sale_validity_auto_cancel/models/res_config_settings.py
odoo/addons/sale_validity_auto_cancel/models/res_partner.py
odoo/addons/sale_validity_auto_cancel/models/sale_order.py
odoo/addons/sale_validity_auto_cancel/readme/CONFIGURE.md
odoo/addons/sale_validity_auto_cancel/readme/CONTRIBUTORS.md
odoo/addons/sale_validity_auto_cancel/readme/DESCRIPTION.md
odoo/addons/sale_validity_auto_cancel/readme/USAGE.md
odoo/addons/sale_validity_auto_cancel/static/description/icon.png
odoo/addons/sale_validity_auto_cancel/static/description/index.html
odoo/addons/sale_validity_auto_cancel/tests/__init__.py
odoo/addons/sale_validity_auto_cancel/tests/test_sale_validity_auto_cancel.py
odoo/addons/sale_validity_auto_cancel/views/res_config_settings.xml
odoo/addons/sale_validity_auto_cancel/views/res_partner_views.xml
odoo_addon_sale_validity_auto_cancel-17.0.1.0.0.5.dist-info/METADATA
odoo_addon_sale_validity_auto_cancel-17.0.1.0.0.5.dist-info/WHEEL
odoo_addon_sale_validity_auto_cancel-17.0.1.0.0.5.dist-info/top_level.txt
odoo_addon_sale_validity_auto_cancel-17.0.1.0.0.5.dist-info/RECORD
